quimb/__init__.py
quimb/_version.py
quimb/calc.py
quimb/core.py
quimb/evo.py
quimb/gates.py
quimb/schematic.py
quimb/utils.py
quimb/experimental/__init__.py
quimb/experimental/autojittn.py
quimb/experimental/cluster_update.py
quimb/experimental/merabuilder demo.ipynb
quimb/experimental/merabuilder.py
quimb/experimental/schematic.py
quimb/experimental/tn_marginals.py
quimb/experimental/tnvmc.py
quimb/experimental/belief_propagation/__init__.py
quimb/experimental/belief_propagation/bp_common.py
quimb/experimental/belief_propagation/d1bp.py
quimb/experimental/belief_propagation/d2bp.py
quimb/experimental/belief_propagation/hd1bp.py
quimb/experimental/belief_propagation/hv1bp.py
quimb/experimental/belief_propagation/l1bp.py
quimb/experimental/belief_propagation/l2bp.py
quimb/experimental/belief_propagation/regions.py
quimb/experimental/operatorbuilder/__init__.py
quimb/experimental/operatorbuilder/operatorbuilder demo.ipynb
quimb/experimental/operatorbuilder/operatorbuilder.py
quimb/gen/__init__.py
quimb/gen/operators.py
quimb/gen/rand.py
quimb/gen/states.py
quimb/linalg/__init__.py
quimb/linalg/approx_spectral.py
quimb/linalg/autoblock.py
quimb/linalg/base_linalg.py
quimb/linalg/mpi_launcher.py
quimb/linalg/numpy_linalg.py
quimb/linalg/rand_linalg.py
quimb/linalg/scipy_linalg.py
quimb/linalg/slepc_linalg.py
quimb/tensor/__init__.py
quimb/tensor/array_ops.py
quimb/tensor/circuit.py
quimb/tensor/circuit_gen.py
quimb/tensor/contraction.py
quimb/tensor/decomp.py
quimb/tensor/drawing.py
quimb/tensor/fitting.py
quimb/tensor/geometry.py
quimb/tensor/interface.py
quimb/tensor/networking.py
quimb/tensor/optimize.py
quimb/tensor/tensor_1d.py
quimb/tensor/tensor_1d_compress.py
quimb/tensor/tensor_1d_tebd.py
quimb/tensor/tensor_2d.py
quimb/tensor/tensor_2d_compress.py
quimb/tensor/tensor_2d_tebd.py
quimb/tensor/tensor_3d.py
quimb/tensor/tensor_3d_tebd.py
quimb/tensor/tensor_approx_spectral.py
quimb/tensor/tensor_arbgeom.py
quimb/tensor/tensor_arbgeom_compress.py
trajectree_quimb-0.0.2.dist-info/METADATA
trajectree_quimb-0.0.2.dist-info/WHEEL
trajectree_quimb-0.0.2.dist-info/licenses/LICENSE.txt
trajectree_quimb-0.0.2.dist-info/RECORD
