Metadata-Version: 2.4
Name: trajectree-quimb
Version: 0.0.2
Summary: Modified version of the Quimb library to work with the Trajectree Quantum optics simulator.
Project-URL: Repository, https://github.com/anshsingal/trajectree-quimb
Author-email: Ansh Singal <asingal@u.northwestern.edu>
License: Apache-2.0
License-File: LICENSE.txt
Keywords: dmrg,mera,networks,peps,physics,quantum,tebd,tensor,tensors
Classifier: Development Status :: 3 - Alpha
Classifier: License :: OSI Approved :: Apache Software License
Classifier: Programming Language :: Python :: 3
Classifier: Programming Language :: Python :: 3.9
Classifier: Programming Language :: Python :: 3.10
Classifier: Programming Language :: Python :: 3.11
Classifier: Programming Language :: Python :: 3.12
Requires-Python: >=3.9
Requires-Dist: autoray>=0.6.12
Requires-Dist: cotengra>=0.6.1
Requires-Dist: cytoolz>=0.8.0
Requires-Dist: numba>=0.39
Requires-Dist: numpy>=1.17
Requires-Dist: psutil>=4.3.1
Requires-Dist: scipy>=1.0.0
Requires-Dist: tqdm>=4
Provides-Extra: advanced-solvers
Requires-Dist: mpi4py; extra == 'advanced-solvers'
Requires-Dist: petsc4py; extra == 'advanced-solvers'
Requires-Dist: slepc4py; extra == 'advanced-solvers'
Provides-Extra: docs
Requires-Dist: astroid<3.0.0; extra == 'docs'
Requires-Dist: autoray>=0.6.12; extra == 'docs'
Requires-Dist: cotengra>=0.6.1; extra == 'docs'
Requires-Dist: doc2dash>=2.4.1; extra == 'docs'
Requires-Dist: furo; extra == 'docs'
Requires-Dist: ipython!=8.7.0; extra == 'docs'
Requires-Dist: myst-nb; extra == 'docs'
Requires-Dist: setuptools-scm; extra == 'docs'
Requires-Dist: sphinx-autoapi; extra == 'docs'
Requires-Dist: sphinx-copybutton; extra == 'docs'
Requires-Dist: sphinx-design; extra == 'docs'
Requires-Dist: sphinx>=2.0; extra == 'docs'
Provides-Extra: tensor
Requires-Dist: matplotlib>=2.0; extra == 'tensor'
Requires-Dist: networkx>=2.3; extra == 'tensor'
Provides-Extra: tests
Requires-Dist: coverage; extra == 'tests'
Requires-Dist: pytest; extra == 'tests'
Requires-Dist: pytest-cov; extra == 'tests'
